portainer/__init__.py
portainer/const.py
portainer/docker_container.py
portainer/endpoint.py
portainer/exceptions.py
portainer/portainer.py
py_portainer_api-0.0.3.dist-info/LICENSE
py_portainer_api-0.0.3.dist-info/METADATA
py_portainer_api-0.0.3.dist-info/WHEEL
py_portainer_api-0.0.3.dist-info/top_level.txt
py_portainer_api-0.0.3.dist-info/RECORD
