Metadata-Version: 2.1
Name: py-portainer-api
Version: 0.0.3
Summary: Python API for communication with Portainer
Author: Lode Smets (lodesmets)
License: MIT
Project-URL: Repository, https://github.com/lodesmets/py-portainer-api
Keywords: portainer
Requires-Python: >=3.10.0
License-File: LICENSE
Requires-Dist: aiohttp
